Metadata-Version: 2.1
Name: django-inline-actions
Version: 2.3.0
Summary: django-inline-actions adds actions to each row of the ModelAdmin or InlineModelAdmin.
Home-page: https://github.com/escaped/django-inline-actions
License: BSD-3-Clause
Author: Alexander Frenzel
Author-email: alex@relatedworks.com
Requires-Python: >=3.5,<4.0
Classifier: Development Status :: 5 - Production/Stable
Classifier: Environment :: Web Environment
Classifier: Framework :: Django
Classifier: Intended Audience :: Developers
Classifier: License :: OSI Approved :: BSD License
Classifier: Operating System :: OS Independent
Classifier: Programming Language :: Python
Classifier: Programming Language :: Python :: 3
Classifier: Programming Language :: Python :: 3.5
Classifier: Programming Language :: Python :: 3.6
Classifier: Programming Language :: Python :: 3.7
Classifier: Topic :: Software Development :: Libraries :: Python Modules
Project-URL: Documentation, https://github.com/escaped/django-inline-actions/blob/master/README.md
Project-URL: Repository, https://github.com/escaped/django-inline-actions
